{"cameraMode":{"drawMode":0,"name":"Shaded","section":"Shading Mode"},"sceneLighting":true,"audioPlay":false,"sceneViewState":{"showFog":true,"showMaterialUpdate":false,"showSkybox":true,"showFlares":true,"showImageEffects":true,"showParticleSystems":true},"in2DMode":false,"pivot":{"x":-6.454254150390625,"y":27.44500160217285,"z":-19.650009155273439},"rotation":{"x":-0.23029114305973054,"y":0.7276290059089661,"z":-0.2908667027950287,"w":-0.5781823396682739},"size":581.234619140625,"orthographic":false}